snake_environment/__init__.py
snake_environment/game/__init__.py
snake_environment/game/objects.py
snake_environment/game/snake_game.py
snake_environment/helpers/__init__.py
snake_environment/helpers/helpers.py
snake_environment-0.3.6.dist-info/LICENSE
snake_environment-0.3.6.dist-info/METADATA
snake_environment-0.3.6.dist-info/WHEEL
snake_environment-0.3.6.dist-info/top_level.txt
snake_environment-0.3.6.dist-info/RECORD
