Metadata-Version: 2.1
Name: snake_environment
Version: 0.3.6
Summary: A simple snake environment with 18 states and 4 actions
Author-email: LPengulin <contact@pengulin.com>
Project-URL: Homepage, https://github.com/LPengulin/Python_snake_environment
Project-URL: Issues, https://github.com/LPengulin/Python_snake_environment/issues
Classifier: Programming Language :: Python :: 3
Classifier: License :: OSI Approved :: MIT License
Classifier: Operating System :: OS Independent
Requires-Python: >=3.8
License-File: LICENSE
Requires-Dist: numpy
Requires-Dist: pygame
